{
    "timestamp": "2025-04-03T17:09:13.202402",
    "dictionary_used": "DICT_6X6_100",
    "markers": [
        {
            "id": 70,
            "display_value": "F",
            "type": "ascii",
            "position": {
                "x": 496,
                "y": 2130
            }
        },
        {
            "id": 82,
            "display_value": "R",
            "type": "ascii",
            "position": {
                "x": 1311,
                "y": 2117
            }
        },
        {
            "id": 76,
            "display_value": "L",
            "type": "ascii",
            "position": {
                "x": 2105,
                "y": 2117
            }
        },
        {
            "id": 3,
            "display_value": "3",
            "type": "id",
            "position": {
                "x": 498,
                "y": 2506
            }
        },
        {
            "id": 1,
            "display_value": "1",
            "type": "id",
            "position": {
                "x": 1324,
                "y": 2504
            }
        },
        {
            "id": 4,
            "display_value": "4",
            "type": "id",
            "position": {
                "x": 2123,
                "y": 2501
            }
        }
    ],
    "rows": [
        [
            "F",
            "R",
            "L"
        ],
        [
            "3",
            "1",
            "4"
        ]
    ],
    "sequential_output": "FFFRLLLL",
    "source": "unknown",
    "image_dimensions": "3072x4096"
}